setup.cfg
setup.py
abf/__init__.py
abf/abstract.py
abf/cpu.py
abf/elf.py
abf/exception.py
abf/macho.py
abf/pe.py
abf.egg-info/PKG-INFO
abf.egg-info/SOURCES.txt
abf.egg-info/dependency_links.txt
abf.egg-info/top_level.txt