Metadata-Version: 1.1
Name: abf
Version: 0.1
Summary: Abstract Binary Format manipulation : elf pe mach-o
Home-page: UNKNOWN
Author: Jonathan Salwan
Author-email: jonathan.salwan gmail com
License: GPLv3
Keywords: abstract binary format manipulation elf pe mach-o
Platform: UNKNOWN
Classifier: Operating System :: POSIX
